mcp_semantic_search/__init__.py
mcp_semantic_search/background_indexer.py
mcp_semantic_search/embedder.py
mcp_semantic_search/index_queue.py
mcp_semantic_search/indexer.py
mcp_semantic_search/qdrant_client.py
mcp_semantic_search/server.py
mcp_semantic_search/watcher.py
mcp_semantic_search-0.1.2.dist-info/METADATA
mcp_semantic_search-0.1.2.dist-info/WHEEL
mcp_semantic_search-0.1.2.dist-info/entry_points.txt
mcp_semantic_search-0.1.2.dist-info/licenses/LICENSE
mcp_semantic_search-0.1.2.dist-info/RECORD
