Metadata-Version: 2.4
Name: mcp-semantic-search
Version: 0.1.2
Summary: MCP server for semantic code search
Project-URL: Homepage, https://github.com/rohithmahesh3/mcp-semantic-search
Project-URL: Repository, https://github.com/rohithmahesh3/mcp-semantic-search
Project-URL: Issues, https://github.com/rohithmahesh3/mcp-semantic-search/issues
Author-email: Rohith Mahesh <rohithmahesh3@gmail.com>
License: MIT
License-File: LICENSE
Keywords: code-search,embeddings,mcp,qdrant,semantic-search
Classifier: Development Status :: 3 - Alpha
Classifier: Intended Audience :: Developers
Classifier: License :: OSI Approved :: MIT License
Classifier: Programming Language :: Python :: 3
Classifier: Programming Language :: Python :: 3.12
Classifier: Programming Language :: Python :: 3.13
Classifier: Topic :: Software Development :: Code Generators
Classifier: Topic :: Software Development :: Libraries :: Python Modules
Requires-Python: >=3.12
Requires-Dist: fastmcp>=0.15.0
Requires-Dist: google-genai>=1.0.0
Requires-Dist: pathspec>=0.12.0
Requires-Dist: python-dotenv>=1.0.0
Requires-Dist: qdrant-client>=1.12.0
Requires-Dist: watchdog>=4.0.0
